Metadata-Version: 2.1
Name: crypto-capsule
Version: 0.0.2
Summary: Just a small script based on python cryptography and electrum mnemonics to encapsulate your secrets.
Home-page: https://github.com/vladiuz1/crypto-capsule
Author: Vlad Smirnov
Author-email: vlad@smirnov.com
Requires-Python: >=3.8, <4
License-File: LICENSE
